{
  "document_id": "20260706_114046_ea6e1557",
  "created_at": "2026-07-06T11:40:46.095710+00:00",
  "project_name": "Wardrobe_Recommendation_Engine-main",
  "scan_id": "20260706_113953_b23353fe",
  "understanding_id": "20260706_114046_db32593f",
  "document_type": "html",
  "update_type": "initial",
  "previous_document_id": null,
  "comparison_summary": null,
  "document_file": "C:\\Users\\PratimMangaldasDasud\\PycharmProjects\\AutoDocX\\workspace\\documents\\Wardrobe_Recommendation_Engine-main\\20260706_114046_ea6e1557.html",
  "metadata_file": "C:\\Users\\PratimMangaldasDasud\\PycharmProjects\\AutoDocX\\workspace\\documents\\Wardrobe_Recommendation_Engine-main\\20260706_114046_ea6e1557.json"
}